{
  "project_info": {
    "project_number": "964052480309",
    "firebase_url": "https://tesigoapp.firebaseio.com",
    "project_id": "tesigoapp",
    "storage_bucket": "tesigoapp.appspot.com"
  },
  "client": [
    {
      "client_info": {
        "mobilesdk_app_id": "1:964052480309:android:b61dc5e9541fee97",
        "android_client_info": {
          "package_name": "com.apptesis"
        }
      },
      "oauth_client": [
        {
          "client_id": "964052480309-hjt9ncp7lcekt29pj8vkpgtelfgj5uom.apps.googleusercontent.com",
          "client_type": 3
        }
      ],
      "api_key": [
        {
          "current_key": "AIzaSyB6v-Zvc4Kg-3PeIDsZ5v5C8f1fVTUZ5LY"
        }
      ],
      "services": {
        "analytics_service": {
          "status": 1
        },
        "appinvite_service": {
          "status": 1,
          "other_platform_oauth_client": []
        },
        "ads_service": {
          "status": 2
        }
      }
    }
  ],
  "configuration_version": "1"
}